argparse_addons.py
argparse_addons-0.11.0.dist-info/LICENSE
argparse_addons-0.11.0.dist-info/METADATA
argparse_addons-0.11.0.dist-info/WHEEL
argparse_addons-0.11.0.dist-info/top_level.txt
argparse_addons-0.11.0.dist-info/RECORD
