Metadata-Version: 2.1
Name: argparse-addons
Version: 0.11.0
Summary: Additional argparse types and actions.
Home-page: https://github.com/eerimoq/argparse_addons
Author: Erik Moqvist
Author-email: erik.moqvist@gmail.com
License: MIT
Keywords: argparse
Classifier: License :: OSI Approved :: MIT License
Requires-Python: >=3.6
License-File: LICENSE
